[
    {
        "img": "",
        "title": "",
        "text": "",
        "price": 0
    },
    {
        "img": "",
        "title": "",
        "text": "",
        "price": 0
    },
    {
        "img": "",
        "title": "",
        "text": "",
        "price": 0
    },
    {
        "img": "",
        "title": "",
        "text": "",
        "price": 0
    },
    {
        "img": "",
        "title": "",
        "text": "",
        "price": 0
    },
    {
        "img": "",
        "title": "",
        "text": "",
        "price": 0
    },
    {
        "img": "",
        "title": "",
        "text": "",
        "price": 0
    }
]